edx_sga/__init__.py
edx_sga/constants.py
edx_sga/sga.py
edx_sga/showanswer.py
edx_sga/tasks.py
edx_sga/test_settings.py
edx_sga/utils.py
edx_sga/wsgi.py
edx_sga/locale/config.yaml
edx_sga/locale/en/LC_MESSAGES/django.mo
edx_sga/locale/en/LC_MESSAGES/django.po
edx_sga/locale/en/LC_MESSAGES/djangojs.mo
edx_sga/locale/en/LC_MESSAGES/djangojs.po
edx_sga/locale/eo/LC_MESSAGES/django.mo
edx_sga/locale/eo/LC_MESSAGES/django.po
edx_sga/locale/eo/LC_MESSAGES/djangojs.mo
edx_sga/locale/eo/LC_MESSAGES/djangojs.po
edx_sga/locale/fake2/LC_MESSAGES/django.mo
edx_sga/locale/fake2/LC_MESSAGES/django.po
edx_sga/locale/fake2/LC_MESSAGES/djangojs.mo
edx_sga/locale/fake2/LC_MESSAGES/djangojs.po
edx_sga/locale/rtl/LC_MESSAGES/django.mo
edx_sga/locale/rtl/LC_MESSAGES/django.po
edx_sga/locale/rtl/LC_MESSAGES/djangojs.mo
edx_sga/locale/rtl/LC_MESSAGES/djangojs.po
edx_sga/management/__init__.py
edx_sga/management/commands/__init__.py
edx_sga/management/commands/sga_migrate_submissions.py
edx_sga/static/css/edx_sga.css
edx_sga/static/js/bower/URIjs/.bower.json
edx_sga/static/js/bower/URIjs/LICENSE.txt
edx_sga/static/js/bower/URIjs/README.md
edx_sga/static/js/bower/URIjs/bower.json
edx_sga/static/js/bower/URIjs/contributing.md
edx_sga/static/js/bower/URIjs/src/IPv6.js
edx_sga/static/js/bower/URIjs/src/SecondLevelDomains.js
edx_sga/static/js/bower/URIjs/src/URI.fragmentQuery.js
edx_sga/static/js/bower/URIjs/src/URI.fragmentURI.js
edx_sga/static/js/bower/URIjs/src/URI.js
edx_sga/static/js/bower/URIjs/src/URI.min.js
edx_sga/static/js/bower/URIjs/src/URITemplate.js
edx_sga/static/js/bower/URIjs/src/jquery.URI.js
edx_sga/static/js/bower/URIjs/src/jquery.URI.min.js
edx_sga/static/js/bower/URIjs/src/punycode.js
edx_sga/static/js/bower/jquery/.bower.json
edx_sga/static/js/bower/jquery/MIT-LICENSE.txt
edx_sga/static/js/bower/jquery/bower.json
edx_sga/static/js/bower/jquery/src/ajax.js
edx_sga/static/js/bower/jquery/src/attributes.js
edx_sga/static/js/bower/jquery/src/callbacks.js
edx_sga-0.26.0.dist-info/licenses/LICENSE
edx_sga-0.26.0.dist-info/METADATA
edx_sga-0.26.0.dist-info/WHEEL
edx_sga-0.26.0.dist-info/entry_points.txt
edx_sga-0.26.0.dist-info/top_level.txt
edx_sga-0.26.0.dist-info/RECORD
